{ "trading_strategy": { "RSI": { "period": 14, "overbought": 70, "oversold": 30 }, "EMA": { "short_period": 12, "long_period": 26 }, "candle_patterns": [ "Hammer", "Shooting Star", "Bullish Engulfing", "Bearish Engulfing" ], "CALL_SETUP": { "entry_conditions": [ "RSI < 30", "Candle pattern == Bullish Engulfing" ], "exit_conditions": [ "RSI > 60", "Price closes below EMA" ], "position_sizing": { "risk_percentage": 2, "max_positions": 5 } }, "PUT_SETUP": { "entry_conditions": [ "RSI > 70", "Candle pattern == Bearish Engulfing" ], "exit_conditions": [ "RSI < 40", "Price closes above EMA" ], "position_sizing": { "risk_percentage": 2, "max_positions": 5 } }, "daily_rules": { "maximum_trades_per_day": 10, "trading_hours": "09:30-16:00" } } }